[{"RoomId":1,"UserId":2,"UserRole":0,"Id":1},{"RoomId":2,"UserId":2,"UserRole":0,"Id":2},{"RoomId":3,"UserId":3,"UserRole":0,"Id":3},{"RoomId":4,"UserId":3,"UserRole":0,"Id":4},{"RoomId":8,"UserId":4,"UserRole":0,"Id":5},{"RoomId":9,"UserId":4,"UserRole":0,"Id":6},{"RoomId":10,"UserId":4,"UserRole":0,"Id":7},{"RoomId":11,"UserId":4,"UserRole":0,"Id":8},{"RoomId":12,"UserId":4,"UserRole":0,"Id":9},{"RoomId":15,"UserId":4,"UserRole":0,"Id":10},{"RoomId":16,"UserId":4,"UserRole":0,"Id":11},{"RoomId":17,"UserId":4,"UserRole":0,"Id":12},{"RoomId":17,"UserId":0,"UserRole":1,"Id":13},{"RoomId":17,"UserId":0,"UserRole":1,"Id":14},{"RoomId":18,"UserId":0,"UserRole":0,"Id":15},{"RoomId":18,"UserId":4,"UserRole":1,"Id":16},{"RoomId":19,"UserId":3,"UserRole":0,"Id":17},{"RoomId":20,"UserId":5,"UserRole":0,"Id":18},{"RoomId":21,"UserId":6,"UserRole":0,"Id":19}]